NNClass/LoadANN.py
NNClass/MNIST.py
NNClass/NNClass.py
NNClass/Softmax.py
NNClass/Test.py
NNClass/__init__.py
NNClass/__data/MNIST/t10k-images.idx3-ubyte
NNClass/__data/MNIST/t10k-labels.idx1-ubyte
NNClass-0.0.1.dist-info/LICENSE
NNClass-0.0.1.dist-info/METADATA
NNClass-0.0.1.dist-info/WHEEL
NNClass-0.0.1.dist-info/top_level.txt
NNClass-0.0.1.dist-info/RECORD
